mailtmapi/__init__.py
mailtmapi/mailtm.py
mailtmapi/schemas/__init__.py
mailtmapi/schemas/account.py
mailtmapi/schemas/domains.py
mailtmapi/schemas/message.py
mailtmapi/utils/__init__.py
mailtmapi/utils/exceptions.py
mailtmapi/utils/misc.py
mailtmapi-1.1.0.dist-info/METADATA
mailtmapi-1.1.0.dist-info/WHEEL
mailtmapi-1.1.0.dist-info/licenses/LICENSE
mailtmapi-1.1.0.dist-info/RECORD
