Metadata-Version: 2.3
Name: MailTMAPI
Version: 1.1.0
Summary: Python API wrapper for mail.tm
Project-URL: Homepage, https://github.com/prtolem/MailTM
Project-URL: Bug Tracker, https://github.com/prtolem/MailTM/issues
Author-email: prtolem <coder@derkown.ru>
License-File: LICENSE
Classifier: License :: OSI Approved :: GNU General Public License v3 (GPLv3)
Classifier: Operating System :: OS Independent
Classifier: Programming Language :: Python :: 3
Requires-Python: >=3.7
